{
  "topic": "In China employee termination",
  "run_date": "2026-03-07",
  "format": "Pulse-style escalation cost matrix brief",
  "source_mix": {
    "official_legal": [
      {
        "title": "Labor Contract Law of the PRC (English)",
        "url": "http://www.npc.gov.cn/zgrdw/englishnpc/Law/2007-12/13/content_1384064.htm",
        "publisher": "National People's Congress",
        "accessed": "2026-03-07",
        "http_status": "200",
        "last_modified_header": "unknown"
      }
    ],
    "practitioner": [
      {
        "title": "Employment & Labour Laws and Regulations: China",
        "url": "https://iclg.com/practice-areas/employment-and-labour-laws-and-regulations/china",
        "publisher": "ICLG",
        "accessed": "2026-03-07",
        "http_status": "200",
        "last_modified_header": "unknown"
      },
      {
        "title": "Key Recent Developments in China's Employment Law",
        "url": "https://www.littler.com/news-analysis/asap/key-recent-developments-chinas-employment-law-china-us-comparative-perspective",
        "publisher": "Littler",
        "accessed": "2026-03-07",
        "http_status": "200",
        "last_modified_header": "Fri, 06 Mar 2026 22:40:53 GMT"
      }
    ],
    "market_business_context": [
      {
        "title": "China Individual - Taxes on personal income",
        "url": "https://taxsummaries.pwc.com/peoples-republic-of-china/individual/taxes-on-personal-income",
        "publisher": "PwC Tax Summaries",
        "accessed": "2026-03-07",
        "http_status": "302",
        "last_modified_header": "unknown"
      },
      {
        "title": "China Human Resources and Payroll Guide",
        "url": "https://www.china-briefing.com/doing-business-guide/china/human-resources-and-payroll",
        "publisher": "China Briefing",
        "accessed": "2026-03-07",
        "http_status": "200",
        "last_modified_header": "unknown"
      }
    ],
    "practical_interpretation": [
      "Escalation-cost matrix for foreign employers",
      "Control triggers by risk and business impact",
      "Settlement-vs-dispute pathway costing"
    ]
  },
  "clustered_themes": [
    "legal route errors",
    "payroll/tax correction cost",
    "manager communication damage",
    "dispute and settlement path costs"
  ],
  "dedupe_actions": [
    "Shifted from route-risk matrix to escalation-cost matrix framing.",
    "Collapsed repeated route sections into impact-by-escalation-level cards."
  ],
  "source_fit_review": {
    "summary": "Core source set remains fit for legal baseline + practitioner interpretation + payroll context.",
    "replacements_needed": "No replacements required; all selected URLs responded during this run.",
    "auto_remediation": "Repeated web_search tool-key issue handled via fallback source-freshness workflow (HTTP status + headers + public accessibility checks), which succeeded."
  },
  "key_uncertainties": [
    "Local dispute outcomes vary by city and case facts.",
    "English materials may lag Chinese-language updates.",
    "IIT treatment of payout components can vary in local implementation."
  ]
}